setup.py
mpqml/My_machine_learning.cp39-win_amd64.pyd
mpqml/__init__.py
mpqml.egg-info/PKG-INFO
mpqml.egg-info/SOURCES.txt
mpqml.egg-info/dependency_links.txt
mpqml.egg-info/requires.txt
mpqml.egg-info/top_level.txt