Metadata-Version: 2.1
Name: mpqml
Version: 0.0.10
Summary: machine learning for MPQ_code
Home-page: https://github.com/miaopeiqi
Author: MPQ
Author-email: miaopeiqi@163.com
License: UNKNOWN
Platform: UNKNOWN
